pyhuskylens/__init__.py
pyhuskylens/pyhuskylens.py
pyhuskylens-2.2.0.dist-info/METADATA
pyhuskylens-2.2.0.dist-info/WHEEL
pyhuskylens-2.2.0.dist-info/top_level.txt
pyhuskylens-2.2.0.dist-info/RECORD
