Metadata-Version: 2.4
Name: pyhuskylens
Version: 2.2.0
Summary: Universal Python library for HuskyLens AI camera - supports MicroPython and CPython (Raspberry Pi)
Author-email: Anton Vanhoucke <anton@antonsmindstorms.com>
License-Expression: MIT
Project-URL: Homepage, https://github.com/antonvh/PyHuskyLens
Project-URL: Documentation, https://github.com/antonvh/PyHuskyLens/blob/master/README.md
Project-URL: Repository, https://github.com/antonvh/PyHuskyLens
Project-URL: Issues, https://github.com/antonvh/PyHuskyLens/issues
Keywords: huskylens,ai,camera,micropython,raspberry-pi,lego,robotics,vision,i2c,serial
Classifier: Development Status :: 5 - Production/Stable
Classifier: Intended Audience :: Developers
Classifier: Intended Audience :: Education
Classifier: Operating System :: OS Independent
Classifier: Programming Language :: Python :: 3
Classifier: Programming Language :: Python :: 3.7
Classifier: Programming Language :: Python :: 3.8
Classifier: Programming Language :: Python :: 3.9
Classifier: Programming Language :: Python :: 3.10
Classifier: Programming Language :: Python :: 3.11
Classifier: Programming Language :: Python :: 3.12
Classifier: Programming Language :: Python :: 3.13
Classifier: Programming Language :: Python :: Implementation :: CPython
Classifier: Programming Language :: Python :: Implementation :: MicroPython
Classifier: Topic :: Education
Classifier: Topic :: Scientific/Engineering :: Artificial Intelligence
Classifier: Topic :: Software Development :: Libraries :: Python Modules
Classifier: Topic :: System :: Hardware
Requires-Python: >=3.7
Provides-Extra: i2c
Requires-Dist: smbus2>=0.4.0; extra == "i2c"
Provides-Extra: serial
Requires-Dist: pyserial>=3.5; extra == "serial"
Provides-Extra: all
Requires-Dist: smbus2>=0.4.0; extra == "all"
Requires-Dist: pyserial>=3.5; extra == "all"
